hatenadiary.py
setup.py
hatenadiary.egg-info/PKG-INFO
hatenadiary.egg-info/SOURCES.txt
hatenadiary.egg-info/dependency_links.txt
hatenadiary.egg-info/top_level.txt