Metadata-Version: 1.0
Name: hatenadiary
Version: 0.3
Summary: A python wrapper around the Hatena Diary AtomPub
Home-page: UNKNOWN
Author: Yoshiori SHOJI
Author-email: yoshiori@google.com
License: UNKNOWN
Platform: UNKNOWN
